erasure_coding-0.2.1.dist-info/METADATA
erasure_coding-0.2.1.dist-info/WHEEL
erasure_coding-0.2.1.dist-info/licenses/LICENSE
erasure_coding/__init__.py
erasure_coding/erasure_coding.cpython-39-x86_64-linux-gnu.so
erasure_coding-0.2.1.dist-info/RECORD
