Metadata-Version: 2.4
Name: erasure_coding
Version: 0.2.1
Classifier: Programming Language :: Rust
Classifier: Programming Language :: Python :: Implementation :: CPython
Classifier: Programming Language :: Python :: Implementation :: PyPy
License-File: LICENSE
Summary: This library provides a simple erasure coding API and way to commit to the resulting erasure coded data using Binary Merkle Tree.
Home-Page: https://github.com/JAMdotTech/py-erasure-coding
Author: JAMdot Technologies
Author-email: JAMdot Technologies <devops@jamdot.tech>
License: Apache-2.0
Requires-Python: >=3.9
Project-URL: Source Code, https://github.com/JAMdotTech/py-erasure-coding
